sir_lancebot/__init__.py
sir_lancebot/__main__.py
sir_lancebot/bot.py
sir_lancebot/constants.py
sir_lancebot/exts/__init__.py
sir_lancebot/exts/avatar_modification/__init__.py
sir_lancebot/exts/avatar_modification/_effects.py
sir_lancebot/exts/avatar_modification/avatar_modify.py
sir_lancebot/exts/core/__init__.py
sir_lancebot/exts/core/error_handler.py
sir_lancebot/exts/core/extensions.py
sir_lancebot/exts/core/help.py
sir_lancebot/exts/core/internal_eval/__init__.py
sir_lancebot/exts/core/internal_eval/_helpers.py
sir_lancebot/exts/core/internal_eval/_internal_eval.py
sir_lancebot/exts/core/ping.py
sir_lancebot/exts/core/source.py
sir_lancebot/exts/events/__init__.py
sir_lancebot/exts/events/hacktoberfest/__init__.py
sir_lancebot/exts/events/hacktoberfest/hacktober_issue_finder.py
sir_lancebot/exts/events/hacktoberfest/hacktoberstats.py
sir_lancebot/exts/events/hacktoberfest/timeleft.py
sir_lancebot/exts/events/trivianight/__init__.py
sir_lancebot/exts/events/trivianight/_game.py
sir_lancebot/exts/events/trivianight/_questions.py
sir_lancebot/exts/events/trivianight/_scoreboard.py
sir_lancebot/exts/events/trivianight/trivianight.py
sir_lancebot/exts/fun/__init__.py
sir_lancebot/exts/fun/anagram.py
sir_lancebot/exts/fun/battleship.py
sir_lancebot/exts/fun/catify.py
sir_lancebot/exts/fun/coinflip.py
sir_lancebot/exts/fun/connect_four.py
sir_lancebot/exts/fun/duck_game.py
sir_lancebot/exts/fun/fun.py
sir_lancebot/exts/fun/game.py
sir_lancebot/exts/fun/hangman.py
sir_lancebot/exts/fun/latex.py
sir_lancebot/exts/fun/madlibs.py
sir_lancebot/exts/fun/magic_8ball.py
sir_lancebot/exts/fun/minesweeper.py
sir_lancebot/exts/fun/movie.py
sir_lancebot/exts/fun/quack.py
sir_lancebot/exts/fun/recommend_game.py
sir_lancebot/exts/fun/rps.py
sir_lancebot/exts/fun/snakes/__init__.py
sir_lancebot/exts/fun/snakes/_converter.py
sir_lancebot/exts/fun/snakes/_snakes_cog.py
sir_lancebot/exts/fun/snakes/_utils.py
sir_lancebot/exts/fun/space.py
sir_lancebot/exts/fun/speedrun.py
sir_lancebot-0.1.0.dist-info/LICENSE
sir_lancebot-0.1.0.dist-info/METADATA
sir_lancebot-0.1.0.dist-info/WHEEL
sir_lancebot-0.1.0.dist-info/RECORD
