Metadata-Version: 2.1
Name: sir-lancebot
Version: 0.1.0
Summary: A Discord bot designed as a fun and beginner-friendly learning environment for writing bot features and learning open-source.
License: MIT
Author: Python Discord
Author-email: info@pythondiscord.com
Requires-Python: ==3.12.*
Classifier: License :: OSI Approved :: MIT License
Classifier: Programming Language :: Python :: 3
Classifier: Programming Language :: Python :: 3.12
Requires-Dist: PyYAML (==6.0.2)
Requires-Dist: arrow (==1.3.0)
Requires-Dist: beautifulsoup4 (==4.12.3)
Requires-Dist: colorama (==0.4.6) ; sys_platform == "win32"
Requires-Dist: coloredlogs (==15.0.1)
Requires-Dist: emoji (==2.12.1)
Requires-Dist: emojis (==0.7.0)
Requires-Dist: lxml (==5.3.0)
Requires-Dist: pillow (==10.4.0)
Requires-Dist: pydantic-settings (==2.2.1)
Requires-Dist: pydantic[dotenv] (==2.6.4)
Requires-Dist: pydis_core[all] (==11.3.1)
Requires-Dist: pyjokes (==0.8.3)
Requires-Dist: rapidfuzz (==3.9.6)
Requires-Dist: sentry-sdk (==2.13.0)
